README.txt
setup.py
minitest/__init__.py
minitest/inject_methods.py
minitest/variables.py
minitest/with_test.py
minitest.egg-info/PKG-INFO
minitest.egg-info/SOURCES.txt
minitest.egg-info/dependency_links.txt
minitest.egg-info/top_level.txt
test/test.py
test/test_class.py
test/test_only.py
test/test_without_test_case.py