Metadata-Version: 1.1
Name: minitest
Version: 2.0.1
Summary: Minitest is inspired by Ruby minispec.
Home-page: https://pypi.python.org/pypi/minitest
Author: Colin Ji
Author-email: jichen3000@gmail.com
License: MIT
Platform: UNKNOWN
Classifier: Programming Language :: Python :: 2
Classifier: Programming Language :: Python :: 3
Classifier: Intended Audience :: Developers
Classifier: License :: OSI Approved :: MIT License
Classifier: Topic :: Software Development :: Libraries
Classifier: Topic :: Utilities
